README.md
pyproject.toml
setup.py
qubolite/__init__.py
qubolite/_c_utils.c
qubolite/_heuristics.py
qubolite/_misc.py
qubolite/assignment.py
qubolite/bitvec.py
qubolite/bounds.py
qubolite/embedding.py
qubolite/preprocessing.py
qubolite/qubo.py
qubolite/sampling.py
qubolite/solving.py
qubolite.egg-info/PKG-INFO
qubolite.egg-info/SOURCES.txt
qubolite.egg-info/dependency_links.txt
qubolite.egg-info/requires.txt
qubolite.egg-info/top_level.txt
test/test_assignment.py