Metadata-Version: 2.1
Name: qubolite
Version: 0.8.5
Summary: Toolbox for quadratic binary optimization
Author-email: Sascha Mücke <sascha.muecke@tu-dortmund.de>, Thore Gerlach <thore.gerlach@iais.fraunhofer.de>, Nico Piatkowski <nico.piatkowski@iais.fraunhofer.de>
Project-URL: Homepage, https://github.com/smuecke/qubolite
Project-URL: Documentation, https://smuecke.github.io/qubolite
Keywords: qubo,optimization,quantum,annealing
Classifier: Programming Language :: Python :: 3
Classifier: Topic :: Scientific/Engineering :: Mathematics
Classifier: Topic :: Scientific/Engineering :: Physics
Requires-Python: >=3.8
Requires-Dist: numpy>=1.23.5
Requires-Dist: networkx>=3.1
Provides-Extra: roof-dual
Requires-Dist: igraph>=0.10.4; extra == "roof-dual"
Provides-Extra: kendall-tau
Requires-Dist: scipy>=1.10.1; extra == "kendall-tau"
Provides-Extra: embedding
Requires-Dist: scikit-learn>=1.2.2; extra == "embedding"
Provides-Extra: preprocessing
Requires-Dist: igraph>=0.10.4; extra == "preprocessing"
Requires-Dist: portion>=2.4.0; extra == "preprocessing"
Provides-Extra: all
Requires-Dist: igraph>=0.10.4; extra == "all"
Requires-Dist: scikit-learn>=1.2.2; extra == "all"
Requires-Dist: portion>=2.4.0; extra == "all"
Requires-Dist: scipy>=1.10.1; extra == "all"
